gestop/__init__.py
gestop/config.py
gestop/dataset.py
gestop/executor.py
gestop/model.py
gestop/mouse_tracker.py
gestop/receiver.py
gestop/recognizer.py
gestop/user_config.py
gestop/data/action_config.json
gestop/data/dynamic_gesture_mapping.json
gestop/data/shrec_gesture_mapping.json
gestop/data/static_gesture_mapping.json
gestop/extend/__init__.py
gestop/extend/dynamic_data_collection.py
gestop/extend/dynamic_train_model.py
gestop/extend/static_data_collection.py
gestop/extend/static_train_model.py
gestop/keypoint_gen/__init__.py
gestop/keypoint_gen/hand_tracking.py
gestop/models/dynamic_net.pth
gestop/models/static_net.pth
gestop/proto/__init__.py
gestop/proto/landmarkList_pb2.py
gestop/util/__init__.py
gestop/util/find_keycode.py
gestop/util/utils.py
gestop-1.0.1.dist-info/LICENSE
gestop-1.0.1.dist-info/METADATA
gestop-1.0.1.dist-info/WHEEL
gestop-1.0.1.dist-info/top_level.txt
gestop-1.0.1.dist-info/RECORD
