Metadata-Version: 2.1
Name: gestop
Version: 1.0.1
Summary: Navigate Desktop with Gestures
Home-page: https://github.com/ofnote/gestop
Author: Sriram Krishna, Nishant Sinha
License: Apache 2.0
Platform: POSIX
Classifier: Environment :: Console
Classifier: Intended Audience :: Developers
Classifier: License :: OSI Approved :: Apache Software License
Classifier: Operating System :: OS Independent
Classifier: Programming Language :: Python :: 3.7
Classifier: Programming Language :: Python :: 3.8
Classifier: Programming Language :: Python :: 3.9
Classifier: Topic :: Software Development
Classifier: Topic :: Scientific/Engineering :: Artificial Intelligence
License-File: LICENSE
Requires-Dist: mediapipe
Requires-Dist: matplotlib
Requires-Dist: pandas
Requires-Dist: protobuf
Requires-Dist: pynput
Requires-Dist: pytorch-lightning
Requires-Dist: scikit-learn
Requires-Dist: torch
Requires-Dist: torchvision
Requires-Dist: wandb
